<PAMDataset>
  <Metadata>
    <MDI key="lat#axis">Y</MDI>
    <MDI key="lat#long_name">latitude</MDI>
    <MDI key="lat#standard_name">latitude</MDI>
    <MDI key="lat#units">degrees_north</MDI>
    <MDI key="lon#axis">X</MDI>
    <MDI key="lon#long_name">longitude</MDI>
    <MDI key="lon#standard_name">longitude</MDI>
    <MDI key="lon#units">degrees_east</MDI>
    <MDI key="NC_GLOBAL#CDI">Climate Data Interface version ?? (http://mpimet.mpg.de/cdi)</MDI>
    <MDI key="NC_GLOBAL#CDO">Climate Data Operators version 1.7.0 (http://mpimet.mpg.de/cdo)</MDI>
    <MDI key="NC_GLOBAL#Conventions">CF-1.4</MDI>
    <MDI key="NC_GLOBAL#global attr">Data Source: Based on COSMO-CLM TERRA_URB run over Kampala for 201401-201412 (see. Brousse et al., 2020)</MDI>
    <MDI key="NC_GLOBAL#history">Wed Apr 21 14:14:08 2021: cdo setgrid,CCLM_001.txt TSI_KAM_2014_06-09_AVG.nc TSI_KAM_2014_06-09_AVG_Grid.nc</MDI>
    <MDI key="NC_GLOBAL#_NCProperties">version=1|netcdflibversion=4.6.1|hdf5libversion=1.10.2</MDI>
    <MDI key="TSI#long_name">Averaged Temperature Suitability Index</MDI>
    <MDI key="TSI#missing_value">nan</MDI>
    <MDI key="TSI#_FillValue">nan</MDI>
  </Metadata>
  <PAMRasterBand band="1">
    <Metadata>
      <MDI key="long_name">Averaged Temperature Suitability Index</MDI>
      <MDI key="missing_value">nan</MDI>
      <MDI key="NETCDF_VARNAME">TSI</MDI>
      <MDI key="STATISTICS_MAXIMUM">0.59526997688096</MDI>
      <MDI key="STATISTICS_MEAN">0.46634828281176</MDI>
      <MDI key="STATISTICS_MINIMUM">0.30881027207663</MDI>
      <MDI key="STATISTICS_STDDEV">0.069852823092793</MDI>
      <MDI key="STATISTICS_VALID_PERCENT">77.16</MDI>
      <MDI key="_FillValue">nan</MDI>
    </Metadata>
  </PAMRasterBand>
</PAMDataset>
